{
    "введение": "assets/введение/",
    "data mining и его применение.": "assets/data mining и его применение/",
    "задачи data mining.": "assets/задачи data mining/",
    "хранилища данных": "assets/хранилища данных/",
    "olap-системы.": "assets/olap-системы/",
    "задача классификации. ч.1": "assets/задача классификации. ч.1/",
    "задача классификации. ч.2": "assets/задача классификации. ч.2/",
    "прогнозирование временных рядов.": "assets/прогнозирование временных рядов/",
    "поиск ассоциативных правил": "assets/поиск ассоциативных правил/",
    "задача кластеризации. ч.1": "assets/задача кластеризации. ч.1/",
    "задача кластеризации. ч.2": "assets/задача кластеризации. ч.2/",
    "задача кластеризации. ч.3": "assets/задача кластеризации. ч.3/",
    "задача кластеризации. ч.4": "assets/задача кластеризации. ч.4/",
    "визуальный анализ данных": "assets/визуальный анализ данных/",
    "стандарты data mining": "assets/стандарты data mining/",
    "процесс data mining": "assets/процесс data mining/"
}